MANIFEST.in
README.rst
dev_requirements.txt
requirements.txt
setup.cfg
setup.py
noaa_radar/__init__.py
noaa_radar/radar.py
noaa_radar/utilities.py
noaa_radar.egg-info/PKG-INFO
noaa_radar.egg-info/SOURCES.txt
noaa_radar.egg-info/dependency_links.txt
noaa_radar.egg-info/entry_points.txt
noaa_radar.egg-info/requires.txt
noaa_radar.egg-info/top_level.txt
scripts/__init__.py
scripts/fetch_radar_image_cli.py