Metadata-Version: 1.1
Name: noaa-radar
Version: 0.7.1
Summary: Tools for downloading and overlaying radar images from the Ridge radar sites.
Home-page: https://github.com/chaddotson/noaa_radar
Author: Chad Dotson
Author-email: chad@cdotson.com
License: GNUv3
Download-URL: https://github.com/chaddotson/noaa_radar/tarball/0.7.0
Keywords: noaa,radar,weather
Platform: UNKNOWN
Classifier: Development Status :: 4 - Beta
Classifier: Topic :: Utilities
Classifier: License :: OSI Approved :: GNU General Public License v3 (GPLv3)
